linauth/__init__.py
linauth/admin.py
linauth/api.py
linauth/apps.py
linauth/emails.py
linauth/models.py
linauth/nofailauth.py
linauth/serializers.py
linauth/tests.py
linauth/urls.py
linhub/__init__.py
linhub/admin.py
linhub/apps.py
linhub/mixins.py
linhub/utils.py
linhub/views.py
linhub-0.1.1.dist-info/licenses/LICENSE
linhub-0.1.1.dist-info/METADATA
linhub-0.1.1.dist-info/WHEEL
linhub-0.1.1.dist-info/entry_points.txt
linhub-0.1.1.dist-info/top_level.txt
linhub-0.1.1.dist-info/RECORD
