Metadata-Version: 2.4
Name: linhub
Version: 0.1.1
Summary: Linguistic Data Hub API
Author-email: Linalgo <admin@linalgo.com>
License: MIT
Project-URL: Homepage, https://github.com/linalgo/linhub
Project-URL: Documentation, https://github.com/linalgo/linhub#readme
Classifier: Development Status :: 4 - Beta
Classifier: Intended Audience :: Developers
Classifier: Programming Language :: Python :: 3.10
Classifier: Framework :: Django
Requires-Python: >=3.10
License-File: LICENSE
Requires-Dist: cachetools==4.1.1
Requires-Dist: certifi==2024.7.4
Requires-Dist: cffi==1.14.3
Requires-Dist: chardet==3.0.4
Requires-Dist: cryptography==43.0.1
Requires-Dist: defusedxml==0.6.0
Requires-Dist: Django==5.0.2
Requires-Dist: django-autoslug==1.9.8
Requires-Dist: django-bulk-update==2.2.0
Requires-Dist: django-cors-headers==4.3.1
Requires-Dist: django-debug-toolbar==4.3.0
Requires-Dist: django-dirtyfields==1.4
Requires-Dist: django-environ==0.11.2
Requires-Dist: django-extensions==3.2.3
Requires-Dist: django-filter==24.1
Requires-Dist: django-guardian==2.4.0
Requires-Dist: django-health-check==3.18.3
Requires-Dist: django-import-export==3.3.6
Requires-Dist: django-jet==1.0.8
Requires-Dist: django-nose==1.4.7
Requires-Dist: django-oauth-toolkit==1.3.2
Requires-Dist: django-organizations==2.5.0
Requires-Dist: django-rest-framework-social-oauth2==1.1.0
Requires-Dist: django-templated-mail==1.1.1
Requires-Dist: djangorestframework==3.15.0
Requires-Dist: djangorestframework-bulk==0.2.1
Requires-Dist: djangorestframework-guardian==0.3.0
Requires-Dist: djangorestframework-simplejwt==5.3.1
Requires-Dist: djoser==2.0.5
Requires-Dist: drf-dynamic-fields==0.3.1
Requires-Dist: drf-nested-routers==0.91
Requires-Dist: drf-spectacular==0.28.0
Requires-Dist: drf-writable-nested==0.6.1
Requires-Dist: drf-yasg==1.17.1
Requires-Dist: flex==6.14.1
Requires-Dist: gunicorn==22.0.0
Requires-Dist: idna==3.7
Requires-Dist: jsonfield==3.1.0
Requires-Dist: nose==1.3.7
Requires-Dist: numpy==1.22.0
Requires-Dist: oauthlib==3.1.0
Requires-Dist: pandas==1.3.5
Requires-Dist: Pillow==9.5.0
Requires-Dist: psutil==5.7.2
Requires-Dist: psycopg2==2.8.6
Requires-Dist: Pygments==2.15.1
Requires-Dist: PyJWT==2.9.0
Requires-Dist: python-dotenv==0.14.0
Requires-Dist: python-jose==3.2.0
Requires-Dist: python3-openid==3.2.0
Requires-Dist: pytz==2020.1
Requires-Dist: requests==2.32.0
Requires-Dist: requests-oauthlib==1.3.0
Requires-Dist: rest-framework-generic-relations==2.0.0
Requires-Dist: scikit-learn==1.3.2
Requires-Dist: scipy==1.7.3
Requires-Dist: six==1.15.0
Requires-Dist: social-auth-app-django==5.4.1
Requires-Dist: social-auth-core==4.4.1
Requires-Dist: swagger-spec-validator>=2.1.0
Requires-Dist: urllib3==1.26.11
Requires-Dist: validators==0.18.1
Dynamic: license-file
